Metadata-Version: 2.1
Name: 365sms
Version: 1.1
Summary: Это библиотека для работы с API сервиса 365SMS
Home-page: https://github.com/Herels2/365smsapi
Author: Sterrist
Author-email: griodred@gmail.com
Project-URL: GitHub, https://github.com/Herels2
Keywords: 365sms sms smsapi 365smsapi 365api
Classifier: Programming Language :: Python :: 3.12
Requires-Python: >=3.6
Requires-Dist: requests
